motionphoto/__init__.py
motionphoto/__main__.py
motionphoto/cli.py
motionphoto/exiftool.config.pl
motionphoto/exiftool.py
motionphoto/google.py
motionphoto/motion.py
motionphoto/samsung.py
motionphoto-0.1.2.dist-info/METADATA
motionphoto-0.1.2.dist-info/WHEEL
motionphoto-0.1.2.dist-info/entry_points.txt
motionphoto-0.1.2.dist-info/top_level.txt
motionphoto-0.1.2.dist-info/RECORD
