Metadata-Version: 2.1
Name: motionphoto
Version: 0.1.2
Summary: Python library for creating Google and Samsung compatible Motion Photos
Home-page: https://github.com/doodspav/motionphoto
Download-URL: https://github.com/doodspav/motionphoto
Author: doodspav
Project-URL: Source, https://github.com/doodspav/motionphoto
Keywords: livephoto,LivePhoto,motionphoto,MotionPhoto
Platform: any
Classifier: Development Status :: 5 - Production/Stable
Classifier: Intended Audience :: Developers
Classifier: Intended Audience :: End Users/Desktop
Classifier: License :: OSI Approved :: Apache Software License
Classifier: Operating System :: OS Independent
Classifier: Programming Language :: Python :: 3
Classifier: Programming Language :: Python :: 3 :: Only
Classifier: Programming Language :: Python :: 3.8
Classifier: Programming Language :: Python :: 3.9
Classifier: Programming Language :: Python :: 3.10
Classifier: Programming Language :: Python :: 3.11
Classifier: Programming Language :: Python :: 3.12
Classifier: Programming Language :: Python :: 3.13
Requires-Python: <4,>=3.8
Requires-Dist: click ~=8.1.7
Requires-Dist: filetype ~=1.2.0
